<?xml version="1.0"?>
<configurator>
  <bitmap name="Feature" type="bitmap32">
    <cluster code="0x001d"/>
    <field mask="0x01" name="TagList"/>
  </bitmap>
  <cluster>
    <attribute code="0x0000" define="DEVICE_LIST" entryType="DeviceTypeStruct" optional="false" side="server" type="ARRAY" writable="false">DeviceTypeList</attribute>
    <attribute code="0x0001" define="SERVER_LIST" entryType="cluster_id" optional="false" side="server" type="ARRAY" writable="false">ServerList</attribute>
    <attribute code="0x0002" define="CLIENT_LIST" entryType="cluster_id" optional="false" side="server" type="ARRAY" writable="false">ClientList</attribute>
    <attribute code="0x0003" define="PARTS_LIST" entryType="endpoint_no" optional="false" side="server" type="ARRAY" writable="false">PartsList</attribute>
    <attribute code="0x0004" define="TAG_LIST" entryType="SemanticTagStruct" length="6" optional="true" side="server" type="ARRAY" writable="false">TagList</attribute>
    <code>0x001d</code>
    <define>DESCRIPTOR_CLUSTER</define>
    <description>The Descriptor Cluster is meant to replace the support from the Zigbee Device Object (ZDO) for describing a node, its endpoints and clusters.</description>
    <domain>General</domain>
    <globalAttribute code="0xFFFD" side="either" value="2"/>
    <name>Descriptor</name>
  </cluster>
  <domain name="CHIP"/>
  <struct name="DeviceTypeStruct">
    <cluster code="0x001d"/>
    <item name="DeviceType" type="devtype_id"/>
    <item name="Revision" type="int16u"/>
  </struct>
  <struct name="SemanticTagStruct">
    <cluster code="0x001d"/>
    <item isNullable="true" name="MfgCode" type="vendor_id"/>
    <item name="NamespaceID" type="enum8"/>
    <item name="Tag" type="enum8"/>
    <item isNullable="true" name="Label" optional="true" type="char_string"/>
  </struct>
</configurator>
