<?xml version="1.0"?>
<configurator>
  <bitmap name="Mode" type="bitmap8">
    <cluster code="0x0102"/>
    <field mask="0x01" name="MotorDirectionReversed"/>
    <field mask="0x02" name="CalibrationMode"/>
    <field mask="0x04" name="MaintenanceMode"/>
    <field mask="0x08" name="LedFeedback"/>
  </bitmap>
  <bitmap name="OperationalStatus" type="bitmap8">
    <cluster code="0x0102"/>
    <field mask="0x03" name="Global"/>
    <field mask="0x0C" name="Lift"/>
    <field mask="0x30" name="Tilt"/>
  </bitmap>
  <bitmap name="ConfigStatus" type="bitmap8">
    <cluster code="0x0102"/>
    <field mask="0x01" name="Operational"/>
    <field mask="0x02" name="OnlineReserved"/>
    <field mask="0x04" name="LiftMovementReversed"/>
    <field mask="0x08" name="LiftPositionAware"/>
    <field mask="0x10" name="TiltPositionAware"/>
    <field mask="0x20" name="LiftEncoderControlled"/>
    <field mask="0x40" name="TiltEncoderControlled"/>
  </bitmap>
  <bitmap name="SafetyStatus" type="bitmap16">
    <cluster code="0x0102"/>
    <field mask="0x0001" name="RemoteLockout"/>
    <field mask="0x0002" name="TamperDetection"/>
    <field mask="0x0004" name="FailedCommunication"/>
    <field mask="0x0008" name="PositionFailure"/>
    <field mask="0x0010" name="ThermalProtection"/>
    <field mask="0x0020" name="ObstacleDetected"/>
    <field mask="0x0040" name="Power"/>
    <field mask="0x0080" name="StopInput"/>
    <field mask="0x0100" name="MotorJammed"/>
    <field mask="0x0200" name="HardwareFailure"/>
    <field mask="0x0400" name="ManualOperation"/>
    <field mask="0x0800" name="Protection"/>
  </bitmap>
  <bitmap name="Feature" type="bitmap32">
    <cluster code="0x0102"/>
    <field mask="0x01" name="Lift"/>
    <field mask="0x02" name="Tilt"/>
    <field mask="0x04" name="PositionAwareLift"/>
    <field mask="0x08" name="AbsolutePosition"/>
    <field mask="0x10" name="PositionAwareTilt"/>
  </bitmap>
  <cluster>
    <attribute code="0x0000" default="0x00" define="WC_TYPE" max="0x09" min="0x00" optional="false" side="server" type="Type" writable="false">Type</attribute>
    <attribute code="0x0001" default="0x0000" define="WC_PHYSICAL_CLOSED_LIMIT_LIFT" max="0xFFFF" min="0x0000" optional="true" side="server" type="int16u" writable="false">PhysicalClosedLimitLift</attribute>
    <attribute code="0x0002" default="0x0000" define="WC_PHYSICAL_CLOSED_LIMIT_TILT" max="0xFFFF" min="0x0000" optional="true" side="server" type="int16u" writable="false">PhysicalClosedLimitTilt</attribute>
    <attribute code="0x0003" define="WC_CURRENT_POSITION_LIFT" isNullable="true" max="0xFFFF" min="0x0000" optional="true" side="server" type="int16u" writable="false">CurrentPositionLift</attribute>
    <attribute code="0x0004" define="WC_CURRENT_POSITION_TILT" isNullable="true" max="0xFFFF" min="0x0000" optional="true" side="server" type="int16u" writable="false">CurrentPositionTilt</attribute>
    <attribute code="0x0005" default="0x0000" define="WC_NUMBER_OF_ACTUATIONS_LIFT" max="0xFFFF" min="0x0000" optional="true" side="server" type="int16u" writable="false">NumberOfActuationsLift</attribute>
    <attribute code="0x0006" default="0x0000" define="WC_NUMBER_OF_ACTUATIONS_TILT" max="0xFFFF" min="0x0000" optional="true" side="server" type="int16u" writable="false">NumberOfActuationsTilt</attribute>
    <attribute code="0x0007" default="0x03" define="WC_CONFIG_STATUS" max="0x7F" min="0x00" optional="false" side="server" type="ConfigStatus" writable="false">ConfigStatus</attribute>
    <attribute code="0x0008" define="WC_CURRENT_POSITION_LIFT_PERCENTAGE" isNullable="true" max="100" min="0" optional="true" reportable="true" side="server" type="percent" writable="false">CurrentPositionLiftPercentage</attribute>
    <attribute code="0x0009" define="WC_CURRENT_POSITION_TILT_PERCENTAGE" isNullable="true" max="100" min="0" optional="true" reportable="true" side="server" type="percent" writable="false">CurrentPositionTiltPercentage</attribute>
    <attribute code="0x000A" default="0x00" define="WC_OPERATIONAL_STATUS" max="0x7F" min="0x00" optional="false" reportable="true" side="server" type="OperationalStatus" writable="false">OperationalStatus</attribute>
    <attribute code="0x000B" define="WC_TARGET_POSITION_LIFT_PERCENT100THS" isNullable="true" max="10000" min="0" optional="true" reportable="true" side="server" type="percent100ths" writable="false">TargetPositionLiftPercent100ths</attribute>
    <attribute code="0x000C" define="WC_TARGET_POSITION_TILT_PERCENT100THS" isNullable="true" max="10000" min="0" optional="true" reportable="true" side="server" type="percent100ths" writable="false">TargetPositionTiltPercent100ths</attribute>
    <attribute code="0x000D" default="0x00" define="WC_END_PRODUCT_TYPE" max="0x20" min="0x00" optional="false" side="server" type="EndProductType" writable="false">EndProductType</attribute>
    <attribute code="0x000E" define="WC_CURRENT_POSITION_LIFT_PERCENT100THS" isNullable="true" max="10000" min="0" optional="true" reportable="true" side="server" type="percent100ths" writable="false">CurrentPositionLiftPercent100ths</attribute>
    <attribute code="0x000F" define="WC_CURRENT_POSITION_TILT_PERCENT100THS" isNullable="true" max="10000" min="0" optional="true" reportable="true" side="server" type="percent100ths" writable="false">CurrentPositionTiltPercent100ths</attribute>
    <attribute code="0x0010" default="0x0000" define="WC_INSTALLED_OPEN_LIMIT_LIFT" max="0xFFFF" min="0x0000" optional="true" side="server" type="int16u" writable="false">InstalledOpenLimitLift</attribute>
    <attribute code="0x0011" default="0xFFFF" define="WC_INSTALLED_CLOSED_LIMIT_LIFT" max="0xFFFF" min="0x0000" optional="true" side="server" type="int16u" writable="false">InstalledClosedLimitLift</attribute>
    <attribute code="0x0012" default="0x0000" define="WC_INSTALLED_OPEN_LIMIT_TILT" max="0xFFFF" min="0x0000" optional="true" side="server" type="int16u" writable="false">InstalledOpenLimitTilt</attribute>
    <attribute code="0x0013" default="0xFFFF" define="WC_INSTALLED_CLOSED_LIMIT_TILT" max="0xFFFF" min="0x0000" optional="true" side="server" type="int16u" writable="false">InstalledClosedLimitTilt</attribute>
    <attribute code="0x0017" default="0x00" define="WC_MODE" max="0x0F" min="0x00" optional="false" side="server" type="Mode" writable="true">
      <access op="read" role="view"/>
      <access op="write" role="manage"/>
      <description>Mode</description>
    </attribute>
    <attribute code="0x001A" default="0x0000" define="WC_SAFETY_STATUS" max="0xFFFF" min="0x0000" optional="true" reportable="true" side="server" type="SafetyStatus" writable="false">SafetyStatus</attribute>
    <client init="false" tick="false">true</client>
    <code>0x0102</code>
    <command cli="zcl WindowCovering UpOrOpen" code="0x00" name="UpOrOpen" optional="false" source="client">
      <description>Moves window covering to InstalledOpenLimitLift and InstalledOpenLimitTilt</description>
    </command>
    <command cli="zcl WindowCovering DownOrClose" code="0x01" name="DownOrClose" optional="false" source="client">
      <description>Moves window covering to InstalledClosedLimitLift and InstalledCloseLimitTilt</description>
    </command>
    <command cli="zcl WindowCovering StopMotion" code="0x02" name="StopMotion" optional="false" source="client">
      <description>Stop any adjusting of window covering</description>
    </command>
    <command cli="zcl WindowCovering GoToLiftValue" code="0x04" name="GoToLiftValue" optional="true" source="client">
      <arg name="liftValue" type="int16u"/>
      <description>Go to lift value specified</description>
    </command>
    <command cli="zcl WindowCovering GoToLiftPercentage" code="0x05" name="GoToLiftPercentage" optional="true" source="client">
      <arg name="liftPercent100thsValue" type="percent100ths"/>
      <description>Go to lift percentage specified</description>
    </command>
    <command cli="zcl WindowCovering GoToTiltValue" code="0x07" name="GoToTiltValue" optional="true" source="client">
      <arg name="tiltValue" type="int16u"/>
      <description>Go to tilt value specified</description>
    </command>
    <command cli="zcl WindowCovering GoToTiltPercentage" code="0x08" name="GoToTiltPercentage" optional="true" source="client">
      <arg name="tiltPercent100thsValue" type="percent100ths"/>
      <description>Go to tilt percentage specified</description>
    </command>
    <define>WINDOW_COVERING_CLUSTER</define>
    <description>Provides an interface for controlling and adjusting automatic window coverings. </description>
    <domain>Closures</domain>
    <globalAttribute code="0xFFFD" side="either" value="5"/>
    <name>Window Covering</name>
    <server init="false" tick="false">true</server>
    <tag description="Lift Control" name="LF"/>
    <tag description="Tilt Control" name="TL"/>
    <tag description="Position Aware Lift" name="PA_LF"/>
    <tag description="Absolute Positioning" name="ABS"/>
    <tag description="Position Aware Tilt" name="PA_TL"/>
  </cluster>
  <domain name="CHIP"/>
  <enum name="Type" type="enum8">
    <cluster code="0x0102"/>
    <item name="RollerShade" value="00"/>
    <item name="RollerShade2Motor" value="01"/>
    <item name="RollerShadeExterior" value="02"/>
    <item name="RollerShadeExterior2Motor" value="03"/>
    <item name="Drapery" value="04"/>
    <item name="Awning" value="05"/>
    <item name="Shutter" value="06"/>
    <item name="TiltBlindTiltOnly" value="07"/>
    <item name="TiltBlindLiftAndTilt" value="08"/>
    <item name="ProjectorScreen" value="09"/>
    <item name="Unknown" value="255"/>
  </enum>
  <enum name="EndProductType" type="enum8">
    <cluster code="0x0102"/>
    <item name="RollerShade" value="00"/>
    <item name="RomanShade" value="01"/>
    <item name="BalloonShade" value="02"/>
    <item name="WovenWood" value="03"/>
    <item name="PleatedShade" value="04"/>
    <item name="CellularShade" value="05"/>
    <item name="LayeredShade" value="06"/>
    <item name="LayeredShade2D" value="07"/>
    <item name="SheerShade" value="08"/>
    <item name="TiltOnlyInteriorBlind" value="09"/>
    <item name="InteriorBlind" value="10"/>
    <item name="VerticalBlindStripCurtain" value="11"/>
    <item name="InteriorVenetianBlind" value="12"/>
    <item name="ExteriorVenetianBlind" value="13"/>
    <item name="LateralLeftCurtain" value="14"/>
    <item name="LateralRightCurtain" value="15"/>
    <item name="CentralCurtain" value="16"/>
    <item name="RollerShutter" value="17"/>
    <item name="ExteriorVerticalScreen" value="18"/>
    <item name="AwningTerracePatio" value="19"/>
    <item name="AwningVerticalScreen" value="20"/>
    <item name="TiltOnlyPergola" value="21"/>
    <item name="SwingingShutter" value="22"/>
    <item name="SlidingShutter" value="23"/>
    <item name="Unknown" value="255"/>
  </enum>
</configurator>
